flask_rstpages
