Metadata-Version: 1.1
Name: Flask-RSTPages
Version: 0.2
Summary: Adds support for reStructuredText to a Flask application
Home-page: http://flask-rstpages.readthedocs.org/
Author: Simon Conseil
Author-email: simon.conseil@gmail.com
License: BSD
Platform: any
Classifier: Environment :: Web Environment
Classifier: Intended Audience :: Developers
Classifier: License :: OSI Approved :: BSD License
Classifier: Operating System :: OS Independent
Classifier: Programming Language :: Python
Classifier: Topic :: Internet :: WWW/HTTP :: Dynamic Content
Classifier: Topic :: Software Development :: Libraries :: Python Modules
